README.md
setup.cfg
setup.py
mera_photo/face_detect.py
mera_photo/file_handler.py
mera_photo/main.py
mera_photo/tests.py
mera_photo.egg-info/PKG-INFO
mera_photo.egg-info/SOURCES.txt
mera_photo.egg-info/dependency_links.txt
mera_photo.egg-info/entry_points.txt
mera_photo.egg-info/not-zip-safe
mera_photo.egg-info/requires.txt
mera_photo.egg-info/top_level.txt