Metadata-Version: 1.1
Name: mera-photo
Version: 0.1.5
Summary: Short for mera photo's bhej dena(Do remember to send me my pics). A photo sorter that sorts photos with respect to faces.
Home-page: https://github.com/PandaWhoCodes/mera_photo
Author: Thomas Ashish Cherian
Author-email: ufoundashish@gmail.com
License: MIT
Platform: any
Classifier: Development Status :: 4 - Beta
Classifier: Environment :: Console
Classifier: Intended Audience :: Developers
Classifier: License :: OSI Approved :: BSD License
Classifier: Operating System :: POSIX
Classifier: Operating System :: MacOS
Classifier: Operating System :: Unix
Classifier: Operating System :: Microsoft :: Windows
Classifier: Programming Language :: Python
Classifier: Programming Language :: Python :: 2
Classifier: Programming Language :: Python :: 3
Classifier: Topic :: Software Development :: Libraries :: Python Modules
